{"shaz_ex_desc_field":{"status":"1","html":"<table class=\"employees\">\n  <thead>\n    <tr>\n      <th>\n        #\n      <\/th>\n      <th>\n        Last Name\n      <\/th>\n      <th>\n        First Name\n      <\/th>\n      <th>\n        Emp ID\n      <\/th>\n      <th>\n        Salary\n      <\/th>\n      <th>\n        FTE %\n      <\/th>\n    <\/tr>\n  <\/thead>\n  <tbody>\n    <tr>\n      <th>\n        1\n      <\/th>\n      <td class=\"shazam\">\n        shaz_ex_last_name_1\n      <\/td>\n      <td class=\"shazam\">\n        shaz_ex_first_name_1\n      <\/td>\n      <td class=\"shazam\">\n        shaz_ex_emp_id_1\n      <\/td>\n      <td>\n        <span>$<\/span><span class=\"shazam\">shaz_ex_salary_1<\/span>\n      <\/td>\n      <td class=\"shazam\">\n        shaz_ex_fte_1\n      <\/td>\n    <\/tr>\n    <tr shazam-mirror-visibility=\"shaz_ex_last_name_2\">\n      <th>\n        2\n      <\/th>\n      <td class=\"shazam\">\n        shaz_ex_last_name_2\n      <\/td>\n      <td class=\"shazam\">\n        shaz_ex_first_name_2\n      <\/td>\n      <td class=\"shazam\">\n        shaz_ex_emp_id_2\n      <\/td>\n      <td>\n        <span>$<\/span><span class=\"shazam\">shaz_ex_salary_2<\/span>\n      <\/td>\n      <td class=\"shazam\">\n        shaz_ex_fte_2\n      <\/td>\n    <\/tr>\n    <tr shazam-mirror-visibility=\"shaz_ex_last_name_3\">\n      <th>\n        3\n      <\/th>\n      <td class=\"shazam\">\n        shaz_ex_last_name_3\n      <\/td>\n      <td class=\"shazam\">\n        shaz_ex_first_name_3\n      <\/td>\n      <td class=\"shazam\">\n        shaz_ex_emp_id_3\n      <\/td>\n      <td>\n        <span>$<\/span><span class=\"shazam\">shaz_ex_salary_3<\/span>\n      <\/td>\n      <td class=\"shazam\">\n        shaz_ex_fte_3\n      <\/td>\n    <\/tr>\n    <tr shazam-mirror-visibility=\"shaz_ex_last_name_4\">\n      <th>\n        4\n      <\/th>\n      <td class=\"shazam\">\n        shaz_ex_last_name_4\n      <\/td>\n      <td class=\"shazam\">\n        shaz_ex_first_name_4\n      <\/td>\n      <td class=\"shazam\">\n        shaz_ex_emp_id_4\n      <\/td>\n      <td>\n        <span>$<\/span><span class=\"shazam\">shaz_ex_salary_4<\/span>\n      <\/td>\n      <td class=\"shazam\">\n        shaz_ex_fte_4\n      <\/td>\n    <\/tr>\n    <tr class=\"spacer\">\n        <td colspan=6><\/td>\n    <\/tr>\n    <tr class=\"total-row\">\n      <th colspan=4>\n        TOTALS\n      <\/th>\n      <td>\n        <span>$<\/span><span class=\"shazam\">shaz_ex_sum_salary<\/span>\n      <\/td>\n      <td class=\"shazam\">\n        shaz_ex_sum_fte\n      <\/td>\n    <\/tr>\n  <\/tbody>\n<\/table>\n","css":"\/* Make the TH cells be bold *\/\n.employees th { font-weight:bold; }\n\n\/* Make the first column be a 50px wide *\/\n.employees tr th:first-child { width: 50px; }\n\n\/* Right-align the last 3 columns headers *\/\n.employees tr th:nth-child(n+4) {\n    text-align:right;\n    padding-right: 20px;\n}\n.employees tr td:nth-child(n+4) input {\n    text-align:right;\n}\n\n\/* add a spacer between the last and the total row *\/\n.employees .spacer {\n    height: 10px;\n}\n\n\/* make a line separating the total cells from the rest of the table *\/\n.employees .total-row td {\n    font-size: 16px;\n    border-top: 1px solid black; \n    padding-top: 10px;\n}\n\n\/* right-align the sum as well *\/\n.employees .total-row td input {\n    text-align:right;\n}\n\n\/* Hide the 'View Equation' links next to the calc fields for sums *\/\n.employees .total-row td a { display: none; }\n\n\/* Hide the question number column on surveys *\/\n.questionnum { display:none !important; }","javascript":""}}